CHANGES.rst
LICENSE
MANIFEST.in
README.rst
setup.py
batteries/__init__.py
batteries/path.py
batteries/util.py
batteries/model/__init__.py
batteries/model/deletable.py
batteries/model/geometric.py
batteries/model/hashable.py
batteries/model/identifiable.py
batteries/model/loggable.py
batteries/model/meta.py
batteries/model/recordable.py
batteries/model/serializable.py
batteries/model/storable.py
batteries/model/types.py
batteries/tests/__init__.py
batteries/tests/test_model.py
batteries/tests/fixtures/test_image.png
sqlalchemy_batteries.egg-info/PKG-INFO
sqlalchemy_batteries.egg-info/SOURCES.txt
sqlalchemy_batteries.egg-info/dependency_links.txt
sqlalchemy_batteries.egg-info/not-zip-safe
sqlalchemy_batteries.egg-info/requires.txt
sqlalchemy_batteries.egg-info/top_level.txt