Metadata-Version: 1.1
Name: sqlalchemy-batteries
Version: 0.4.5
Summary: Various batteries for SQLAlchemy models
Home-page: https://github.com/jessedhillon/batteries
Author: Jesse Dhillon
Author-email: jesse@deva0.net
License: UNKNOWN
Keywords: util paste
Platform: UNKNOWN
Classifier: Programming Language :: Python
